str_to_bool/__init__.py
str_to_bool/_version.py
python_strtobool-1.0.3.dist-info/METADATA
python_strtobool-1.0.3.dist-info/WHEEL
python_strtobool-1.0.3.dist-info/licenses/LICENSE
python_strtobool-1.0.3.dist-info/RECORD
