Metadata-Version: 2.3
Name: python-strtobool
Version: 1.0.3
Summary: str_to_bool function for Python
Project-URL: homepage, https://github.com/sassanh/python-strtobool/
Project-URL: repository, https://github.com/sassanh/python-strtobool/
Project-URL: documentation, https://github.com/sassanh/python-strtobool/
Project-URL: changelog, https://github.com/sassanh/python-strtobool/blob/main/CHANGELOG.md
Author-email: Sassan Haradji <me@sassanh.com>
Maintainer-email: Sassan Haradji <me@sassanh.com>
License: Apache-2.0
Keywords: str2bool,str_to_bool,strtobool
Requires-Python: >=3.0
